mop/__init__.py
mop/mop.py
mop_bam-0.0.6.dist-info/LICENSE
mop_bam-0.0.6.dist-info/METADATA
mop_bam-0.0.6.dist-info/WHEEL
mop_bam-0.0.6.dist-info/entry_points.txt
mop_bam-0.0.6.dist-info/top_level.txt
mop_bam-0.0.6.dist-info/RECORD
