Metadata-Version: 2.1
Name: mop-bam
Version: 0.0.6
Summary: Get well-mapped regions from bams
Home-page: https://github.com/RILAB/mop
Author: Silas Tittes
Author-email: silas.tittes@gmail.com
License: GPL-3.0
Keywords: bam files genetics python package
Platform: UNKNOWN
Classifier: Programming Language :: Python :: 3
Classifier: License :: OSI Approved :: MIT License
Classifier: Operating System :: OS Independent
Requires-Python: >=3.6
Requires-Dist: numpy
